xwavelet/__init__.py
xwavelet/classes.py
xwavelet/filtering.py
xwavelet/xrtools.py
xwavelet/tests/test_xrtools.py
xwavelet/wavelets/__init__.py
xwavelet/wavelets/waveletAnalysis.py
xwavelet/wavelets/waveletFunctions.py
xwavelet-0.0.2.dist-info/LICENSE.txt
xwavelet-0.0.2.dist-info/METADATA
xwavelet-0.0.2.dist-info/WHEEL
xwavelet-0.0.2.dist-info/top_level.txt
xwavelet-0.0.2.dist-info/RECORD
