Metadata-Version: 2.1
Name: xwavelet
Version: 0.0.2
Summary: An xarray-based implementation of wavelet analysis
Author-email: John Krasting <john.krasting@noaa.gov>
License: MIT License        
Project-URL: homepage, https://github.com/jkrasting/xwavelet
Project-URL: documentation, https://github.com/jkrasting/xwavelet
Project-URL: repository, https://github.com/jkrasting/xwavelet
Keywords: xarray,wavelet,spectral analysis
Classifier: Development Status :: 3 - Alpha
Classifier: Intended Audience :: Science/Research
Classifier: Topic :: Scientific/Engineering
Classifier: License :: OSI Approved :: MIT License
Classifier: Programming Language :: Python :: 3.8
Classifier: Programming Language :: Python :: 3.9
Requires-Python: >=3.8
License-File: LICENSE.txt
Requires-Dist: matplotlib
Requires-Dist: numpy
Requires-Dist: scipy
Requires-Dist: xarray
Provides-Extra: test
Requires-Dist: pytest ; extra == 'test'
